{
  "date": "12월 6일",
  "fortunes": [
    {
      "animal": "쥐",
      "재물": "보통",
      "건강": "보통",
      "사랑": "질투",
      "길방": "東",
      "본문": "36년생 보면 답답, 안 보면 궁금. 48년생 굿이나 보고 떡만 먹자. 60년생 미운 사람 떡 하나 더 주기. 72년생 형식보다 형편에 맞출 것. 84년생 사공이 많으면 배가 산으로. 96년생 나는 나이기에 특별하다.",
      "년생운세": {
        "36": "보면 답답, 안 보면 궁금",
        "48": "굿이나 보고 떡만 먹자",
        "60": "미운 사람 떡 하나 더 주기",
        "72": "형식보다 형편에 맞출 것",
        "84": "사공이 많으면 배가 산으로",
        "96": "나는 나이기에 특별하다"
      }
    },
    {
      "animal": "소",
      "재물": "무난",
      "건강": "양호",
      "사랑": "기쁨",
      "길방": "北",
      "본문": "37년생 먹을 복이 생길 수도. 49년생 적당한 소비는 삶의 윤활유. 61년생 의미 있는 지출을 할 수. 73년생 계획한 일이 순조롭게 진행. 85년생 지출도 하고 이익도 생길 듯. 97년생 데이트 비용은 넉넉하게.",
      "년생운세": {
        "37": "먹을 복이 생길 수도",
        "49": "적당한 소비는 삶의 윤활유",
        "61": "의미 있는 지출을 할 수",
        "73": "계획한 일이 순조롭게 진행",
        "85": "지출도 하고 이익도 생길 듯",
        "97": "데이트 비용은 넉넉하게"
      }
    },
    {
      "animal": "호랑이",
      "재물": "무난",
      "건강": "양호",
      "사랑": "♥",
      "길방": "東",
      "본문": "38년생 혈육의 정이 피어나는 하루. 50년생 사랑에 나이는 숫자에 불과. 62년생 내 가족은 내가 챙긴다. 74년생 배우자에게 잘해줄 것. 86년생 배우자 말을 존중하면 만사형통. 98년생 사랑 만들기에 좋은 날.",
      "년생운세": {
        "38": "혈육의 정이 피어나는 하루",
        "50": "사랑에 나이는 숫자에 불과",
        "62": "내 가족은 내가 챙긴다",
        "74": "배우자에게 잘해줄 것",
        "86": "배우자 말을 존중하면 만사형통",
        "98": "사랑 만들기에 좋은 날"
      }
    },
    {
      "animal": "토끼",
      "재물": "무난",
      "건강": "양호",
      "사랑": "기쁨",
      "길방": "東",
      "본문": "39년생 버릴 것이 없는 하루. 51년생 남보다 내 핏줄이 좋은 것. 63년생 모든 것은 제 자리가 있는 법. 75년생 집안일은 가족이 힘을 모아라. 87년생 좋은 일엔 사람이 많아야 함. 99년생 오늘은 내가 주인공.",
      "년생운세": {
        "39": "버릴 것이 없는 하루",
        "51": "남보다 내 핏줄이 좋은 것",
        "63": "모든 것은 제 자리가 있는 법",
        "75": "집안일은 가족이 힘을 모아라",
        "87": "좋은 일엔 사람이 많아야 함",
        "99": "오늘은 내가 주인공"
      }
    },
    {
      "animal": "용",
      "재물": "지출",
      "건강": "주의",
      "사랑": "갈등",
      "길방": "西",
      "본문": "40년생 알면 병, 모르면 약. 52년생 열 손가락 깨물어 아프지 않은 것 없다. 64년생 화내지 말고 잔소리 금지. 76년생 나서지 말고 조용히. 88년생 가족이라도 생각이 다를 수. 00년생 예쁜 말, 고운 말 사용.",
      "년생운세": {
        "40": "알면 병, 모르면 약",
        "52": "열 손가락 깨물어 아프지 않은 것 없다",
        "64": "화내지 말고 잔소리 금지",
        "76": "나서지 말고 조용히",
        "88": "가족이라도 생각이 다를 수",
        "00": "예쁜 말, 고운 말 사용"
      }
    },
    {
      "animal": "뱀",
      "재물": "지출",
      "건강": "주의",
      "사랑": "만남",
      "길방": "北",
      "본문": "41년생 사람 많은 곳에 가지 말라. 53년생 몸을 따듯하게 해주자. 65년생 계획에 변화가 생길 수도. 77년생 예상보다 오래 걸릴 수도. 89년생 계획보다 지출이 많아질 수 있다. 01년생 잘못된 만남 가질 수도.",
      "년생운세": {
        "41": "사람 많은 곳에 가지 말라",
        "53": "몸을 따듯하게 해주자",
        "65": "계획에 변화가 생길 수도",
        "77": "예상보다 오래 걸릴 수도",
        "89": "계획보다 지출이 많아질 수 있다",
        "01": "잘못된 만남 가질 수도"
      }
    },
    {
      "animal": "말",
      "재물": "지출",
      "건강": "보통",
      "사랑": "답답",
      "길방": "北",
      "본문": "42년생 말이 아니면 하지 말고 길이 아니면 가지 말라. 54년생 일방적이지 말고 강요도 말라. 66년생 부드러움이 강함을 이길 수도. 78년생 한 박자 느린 것이 더 좋을 수. 90년생 기대했던 것보다 못할 수도.",
      "년생운세": {
        "42": "말이 아니면 하지 말고 길이 아니면 가지 말라",
        "54": "일방적이지 말고 강요도 말라",
        "66": "부드러움이 강함을 이길 수도",
        "78": "한 박자 느린 것이 더 좋을 수",
        "90": "기대했던 것보다 못할 수도"
      }
    },
    {
      "animal": "양",
      "재물": "무난",
      "건강": "양호",
      "사랑": "행복",
      "길방": "東",
      "본문": "43년생 삶이 웃음소리로 채워질 수 있다. 55년생 집안에 행복의 향기가 진동할 수도. 67년생 꿈은 이루어지는 법, 소원을 말해봐. 79년생 목적 달성하고 성취감을 맛볼 수도. 91년생 행운의 신은 내 편일 수도.",
      "년생운세": {
        "43": "삶이 웃음소리로 채워질 수 있다",
        "55": "집안에 행복의 향기가 진동할 수도",
        "67": "꿈은 이루어지는 법, 소원을 말해봐",
        "79": "목적 달성하고 성취감을 맛볼 수도",
        "91": "행운의 신은 내 편일 수도"
      }
    },
    {
      "animal": "원숭이",
      "재물": "보통",
      "건강": "보통",
      "사랑": "베풂",
      "길방": "南",
      "본문": "44년생 아끼는 것도 중요하나 잘 써야 한다. 56년생 물질보다는 사람이 중요함. 68년생 직접 하지 말고 적임자에게 맡겨라. 80년생 적은 것은 양보하고 손해 보는 게 낫다. 92년생 일하지 말고 휴식을 가져라.",
      "년생운세": {
        "44": "아끼는 것도 중요하나 잘 써야 한다",
        "56": "물질보다는 사람이 중요함",
        "68": "직접 하지 말고 적임자에게 맡겨라",
        "80": "적은 것은 양보하고 손해 보는 게 낫다",
        "92": "일하지 말고 휴식을 가져라"
      }
    },
    {
      "animal": "닭",
      "재물": "보통",
      "건강": "보통",
      "사랑": "베풂",
      "길방": "西",
      "본문": "45년생 미우나 고우나 혈육이 좋은 것. 57년생 지나간 일에 집착하지 말 것. 69년생 오지 않은 미래에 대해 걱정 말고 오늘에 충실. 81년생 칭찬과 덕담은 고래도 춤추게 한다. 93년생 상대방에 맞장구쳐 주기.",
      "년생운세": {
        "45": "미우나 고우나 혈육이 좋은 것",
        "57": "지나간 일에 집착하지 말 것",
        "69": "오지 않은 미래에 대해 걱정 말고 오늘에 충실",
        "81": "칭찬과 덕담은 고래도 춤추게 한다",
        "93": "상대방에 맞장구쳐 주기"
      }
    },
    {
      "animal": "개",
      "재물": "무난",
      "건강": "양호",
      "사랑": "기쁨",
      "길방": "南",
      "본문": "46년생 몸에 익숙한 것이 편안한 법이다. 58년생 사람과 술은 오래된 것이 좋은 법. 70년생 십시일반, 서로 힘과 마음을 모아라. 82년생 노력한 일에서 좋은 결실을 거둘 수. 94년생 선물을 주거나 선물을 받자.",
      "년생운세": {
        "46": "몸에 익숙한 것이 편안한 법이다",
        "58": "사람과 술은 오래된 것이 좋은 법",
        "70": "십시일반, 서로 힘과 마음을 모아라",
        "82": "노력한 일에서 좋은 결실을 거둘 수",
        "94": "선물을 주거나 선물을 받자"
      }
    },
    {
      "animal": "돼지",
      "재물": "좋음",
      "건강": "튼튼",
      "사랑": "한마음",
      "길방": "北",
      "본문": "35년생 가족의 화목이 행복의 근본. 47년생 최선을 다하면 하늘도 내 편. 59년생 경사가 생길 수도. 71년생 초대받거나 초대할 수 있다. 83년생 사람이나 물건은 많을수록 좋다. 95년생 너와 나는 한마음이다.",
      "년생운세": {
        "35": "가족의 화목이 행복의 근본",
        "47": "최선을 다하면 하늘도 내 편",
        "59": "경사가 생길 수도",
        "71": "초대받거나 초대할 수 있다",
        "83": "사람이나 물건은 많을수록 좋다",
        "95": "너와 나는 한마음이다"
      }
    }
  ]
}